EP/__init__.py
EP/pi.py
EasyPi-1.2.dist-info/METADATA
EasyPi-1.2.dist-info/WHEEL
EasyPi-1.2.dist-info/top_level.txt
EasyPi-1.2.dist-info/RECORD
