Metadata-Version: 2.1
Name: EasyPi
Version: 1.2
Summary: Easy to use
Home-page: UNKNOWN
Author: 자색치즈고구마
Author-email: author@example.com
License: UNKNOWN
Platform: UNKNOWN
Classifier: Programming Language :: Python :: 3
